pytest_image_diff/__init__.py
pytest_image_diff/__main__.py
pytest_image_diff/_types.py
pytest_image_diff/helpers.py
pytest_image_diff/image_diff.py
pytest_image_diff/plugin.py
pytest_image_diff/splinter.py
pytest_image_diff-0.0.14.dist-info/LICENSE
pytest_image_diff-0.0.14.dist-info/METADATA
pytest_image_diff-0.0.14.dist-info/WHEEL
pytest_image_diff-0.0.14.dist-info/entry_points.txt
pytest_image_diff-0.0.14.dist-info/top_level.txt
pytest_image_diff-0.0.14.dist-info/RECORD
