Metadata-Version: 2.1
Name: pytest-image-diff
Version: 0.0.14
Home-page: https://github.com/Apkawa/pytest-image-diff
Author: Apkawa
Author-email: apkawa@gmail.com
License: MIT
Keywords: pytest
Classifier: Development Status :: 3 - Alpha
Classifier: Framework :: Pytest
Classifier: Intended Audience :: Developers
Classifier: Environment :: Web Environment
Classifier: License :: OSI Approved :: MIT License
Classifier: Programming Language :: Python
Classifier: Programming Language :: Python :: 3
Classifier: Programming Language :: Python :: 3.8
Classifier: Programming Language :: Python :: 3.9
Classifier: Programming Language :: Python :: 3.10
Classifier: Programming Language :: Python :: 3.11
Classifier: Programming Language :: Python :: 3.12
Classifier: Programming Language :: Python :: 3.13
Requires-Python: >=3.6, <4
License-File: LICENSE
Requires-Dist: pytest
Requires-Dist: typing_extensions
Requires-Dist: diffimg
Requires-Dist: imgdiff
Provides-Extra: splinter
Requires-Dist: pytest-splinter>=2.1.0; extra == "splinter"
